{
  "type": "Feature",
  "properties": {
    "gn:elevation": 107,
    "iso:country": "US",
    "name:ceb_x_preferred": [
      "Middle Georgia Regional Airport"
    ],
    "name:eng_x_preferred": [
      "Middle Georgia Regional Airport"
    ],
    "name:eng_x_variant": [
      "MCN",
      "KMCN"
    ],
    "name:fas_x_preferred": [
      "فرودگاه منطقه‌ای میدل جرجیا"
    ],
    "name:jpn_x_preferred": [
      "Middle Georgia地域空港"
    ],
    "name:ron_x_preferred": [
      "Aeroportul Regional Middle Georgia"
    ],
    "name:tgk_x_preferred": [
      "Фурудгоҳи мантақа‌ий мидл ҷрҷио"
    ],
    "name:urd_x_preferred": [
      "مڈل جارجیا ریجنل ہوائی اڈا"
    ],
    "oa:elevation_ft": "354",
    "oa:type": "medium_airport",
    "sfomuseum:is_sfo": 1,
    "sfomuseum:placetype": "airport",
    "wd:wordcount": 1350,
    "woe:hierarchy": {
      "country_id": 23424977,
      "county_id": 12587880,
      "planet_id": 1,
      "state_id": 2347569
    },
    "wof:name": "Middle Georgia Regional Airport",
    "wof:placetype": "campus"
  },
  "geometry": {"coordinates":[-83.6492,32.692799],"type":"Point"}
}
