{
  "type": "Feature",
  "properties": {
    "gn:elevation": 30,
    "iso:country": "US",
    "millsfield:count_images": 4,
    "millsfield:count_objects": 2,
    "name:deu_x_preferred": [
      "Ketchikan International Airport"
    ],
    "name:eng_x_preferred": [
      "Ketchikan International Airport"
    ],
    "name:eng_x_variant": [
      "KTN",
      "PAKT"
    ],
    "name:fas_x_preferred": [
      "فرودگاه بین‌المللی کچیکان"
    ],
    "name:jpn_x_preferred": [
      "ケチカン国際空港"
    ],
    "name:ron_x_preferred": [
      "Aeroportul Ketchikan"
    ],
    "name:rus_x_preferred": [
      "Кетчикан"
    ],
    "name:spa_x_preferred": [
      "Aeropuerto Internacional de Ketchikan"
    ],
    "name:tgk_x_preferred": [
      "Фурудгоҳи бин‌алмилалӣ кчикон"
    ],
    "name:zho_x_preferred": [
      "克奇坎国际机场"
    ],
    "oa:elevation_ft": "89",
    "oa:type": "medium_airport",
    "sfomuseum:count_objects_public": 0,
    "sfomuseum:is_sfo": 1,
    "sfomuseum:name": "Ketchikan International Airport",
    "sfomuseum:placetype": "airport",
    "sfomuseum:repo": "sfomuseum-data-whosonfirst",
    "wd:wordcount": 1578,
    "woe:hierarchy": {
      "country_id": 23424977,
      "county_id": 12587565,
      "planet_id": 1,
      "state_id": 2347560
    },
    "wof:name": "Ketchikan International Airport",
    "wof:placetype": "campus"
  },
  "geometry": {"coordinates":[-131.714004,55.355598],"type":"Point"}
}
