{
  "type": "Feature",
  "properties": {
    "iso:country": "MP",
    "name:deu_x_preferred": [
      "Flughafen Saipan"
    ],
    "name:eng_x_preferred": [
      "Saipan International Airport"
    ],
    "name:eng_x_variant": [
      "SPN",
      "PGSN"
    ],
    "name:fas_x_preferred": [
      "فرودگاه بین‌المللی سایپن"
    ],
    "name:fin_x_preferred": [
      "Saipanin kansainvälinen lentoasema"
    ],
    "name:fra_x_preferred": [
      "Saipan International Airport"
    ],
    "name:heb_x_preferred": [
      "נמל התעופה הבינלאומי של סאיפאן"
    ],
    "name:ind_x_preferred": [
      "Bandar Udara Internasional Saipan"
    ],
    "name:ita_x_preferred": [
      "Saipan International Airport"
    ],
    "name:jpn_x_preferred": [
      "サイパン国際空港"
    ],
    "name:kor_x_preferred": [
      "사이판 국제공항"
    ],
    "name:nld_x_preferred": [
      "Saipan International Airport"
    ],
    "name:pol_x_preferred": [
      "Port lotniczy Saipan"
    ],
    "name:por_x_preferred": [
      "Saipan International Airport"
    ],
    "name:ron_x_preferred": [
      "Aeroportul Internațional Saipan"
    ],
    "name:rus_x_preferred": [
      "Сайпан"
    ],
    "name:spa_x_preferred": [
      "Aeropuerto Internacional de Saipán"
    ],
    "name:swe_x_preferred": [
      "Saipan International Airport"
    ],
    "name:tgk_x_preferred": [
      "Фурудгоҳи бин‌алмилалӣ соипн"
    ],
    "name:vie_x_preferred": [
      "Sân bay quốc tế Saipan"
    ],
    "name:zho_x_preferred": [
      "塞班國際機場"
    ],
    "oa:elevation_ft": "215",
    "oa:type": "medium_airport",
    "sfomuseum:is_sfo": 1,
    "sfomuseum:placetype": "airport",
    "wd:wordcount": 1484,
    "woe:hierarchy": {
      "country_id": 23424788,
      "planet_id": 1,
      "state_id": 29389658
    },
    "wof:name": "Saipan International Airport",
    "wof:placetype": "campus"
  },
  "geometry": {"coordinates":[145.729004,15.119],"type":"Point"}
}
