{
  "type": "Feature",
  "properties": {
    "flysfo:is_sfo": 1,
    "gn:elevation": 1959,
    "iso:country": "US",
    "name:ceb_x_preferred": [
      "Jackson Hole Airport"
    ],
    "name:deu_x_preferred": [
      "Jackson Hole Airport"
    ],
    "name:eng_x_preferred": [
      "Jackson Hole Airport"
    ],
    "name:eng_x_variant": [
      "JAC",
      "KJAC"
    ],
    "name:fas_x_preferred": [
      "فرودگاه جکسن هول"
    ],
    "name:fra_x_preferred": [
      "Aéroport de Jackson Hole"
    ],
    "name:fra_x_variant": [
      "aéroport de Jackson Hole"
    ],
    "name:ita_x_preferred": [
      "Aeroporto di Jackson-Hole"
    ],
    "name:ita_x_variant": [
      "Aeroporto di Jackson Hole"
    ],
    "name:jpn_x_preferred": [
      "ジャクソンホール空港"
    ],
    "name:mar_x_preferred": [
      "जॅक्सन होल विमानतळ"
    ],
    "name:nld_x_preferred": [
      "Jackson Hole Airport"
    ],
    "name:pol_x_preferred": [
      "Port lotniczy Jackson Hole"
    ],
    "name:ron_x_preferred": [
      "Aeroportul Jackson Hole"
    ],
    "name:spa_x_preferred": [
      "Aeropuerto de Jackson Hole"
    ],
    "name:swe_x_preferred": [
      "Jackson Hole Airport"
    ],
    "name:tgk_x_preferred": [
      "Фурудгоҳи ҷксн ҳул"
    ],
    "name:urd_x_preferred": [
      "جیکسن ہول ہوائی اڈا"
    ],
    "name:zho_x_preferred": [
      "傑克遜"
    ],
    "oa:elevation_ft": "6451",
    "oa:type": "medium_airport",
    "sfomuseum:is_sfo": 1,
    "sfomuseum:placetype": "airport",
    "sfomuseum:repo": "sfomuseum-data-whosonfirst",
    "wd:wordcount": 929,
    "woe:hierarchy": {
      "country_id": 23424977,
      "county_id": 12590625,
      "planet_id": 1,
      "state_id": 2347609
    },
    "wof:name": "Jackson Hole Airport",
    "wof:placetype": "campus"
  },
  "geometry": {"coordinates":[-110.737999,43.6073],"type":"Point"}
}
