{
  "type": "Feature",
  "properties": {
    "name:ara_x_preferred": [
      "قاعدة الملك عبد العزيز الجوية"
    ],
    "name:ben_x_preferred": [
      "বাদশাহ আব্দুল আজিজ বিমান ঘাটি"
    ],
    "name:ceb_x_preferred": [
      "King Abdulaziz Air Base"
    ],
    "name:eng_x_preferred": [
      "King Abdulaziz Air Base"
    ],
    "name:eng_x_variant": [
      "DHA",
      "OEDR"
    ],
    "name:fas_x_preferred": [
      "فرودگاه بین‌المللی ظهران"
    ],
    "name:jpn_x_preferred": [
      "キング・アブドラアジズ飛行場"
    ],
    "name:msa_x_preferred": [
      "Pangkalan Udara Raja Abdulaziz"
    ],
    "name:tgk_x_preferred": [
      "Фурудгоҳи бин‌алмилалӣ зҳрон"
    ],
    "name:urd_x_preferred": [
      "شاہ عبدالعزیز ایئر بیس"
    ],
    "name:zho_x_preferred": [
      "Abdulaziz國王空軍基地"
    ],
    "oa:elevation_ft": "84",
    "oa:type": "large_airport",
    "sfomuseum:count_objects_public": 1,
    "sfomuseum:is_sfo": 1,
    "sfomuseum:name": "King Abdulaziz Air Base",
    "sfomuseum:placetype": "airport",
    "woe:hierarchy": {
      "country_id": 23424938,
      "county_id": 56120200,
      "planet_id": 1,
      "state_id": 2346954
    },
    "wof:name": "Dhahran International Airport",
    "wof:placetype": "campus"
  },
  "geometry": {"coordinates":[50.152,26.2654],"type":"Point"}
}
