{
  "type": "Feature",
  "properties": {
    "iso:country": "GU",
    "name:ceb_x_preferred": [
      "USAF Andersen Air Force Base"
    ],
    "name:ces_x_preferred": [
      "Andersenova letecká základna"
    ],
    "name:deu_x_preferred": [
      "Andersen Air Force Base"
    ],
    "name:eng_x_preferred": [
      "Andersen Air Force Base"
    ],
    "name:eng_x_variant": [
      "UAM",
      "PGUA"
    ],
    "name:fas_x_preferred": [
      "پایگاه نیروی هوایی اندرسن"
    ],
    "name:fin_x_preferred": [
      "Andersenin lentotukikohta"
    ],
    "name:fra_x_preferred": [
      "Andersen Air Force Base"
    ],
    "name:fra_x_variant": [
      "base aérienne d'Andersen"
    ],
    "name:ita_x_preferred": [
      "Andersen Air Force Base"
    ],
    "name:jpn_x_preferred": [
      "アンダーセン空軍基地"
    ],
    "name:kor_x_preferred": [
      "앤더슨 공군기지"
    ],
    "name:msa_x_preferred": [
      "Pangkalan Udara Andersen"
    ],
    "name:nld_x_preferred": [
      "Andersen Air Force Base"
    ],
    "name:nob_x_preferred": [
      "Andersen Air Force Base"
    ],
    "name:pol_x_preferred": [
      "Port lotniczy Andersen"
    ],
    "name:rus_x_preferred": [
      "Андерсен"
    ],
    "name:spa_x_preferred": [
      "Base de la Fuerza Aérea Andersen"
    ],
    "name:swe_x_preferred": [
      "USAF Andersen Air Force Base"
    ],
    "name:tgk_x_preferred": [
      "Пойгоҳи Нерӯи Ҳавоии Андерсен"
    ],
    "name:zho_x_preferred": [
      "安德森空军基地"
    ],
    "oa:elevation_ft": "627",
    "oa:type": "medium_airport",
    "sfomuseum:is_sfo": 1,
    "sfomuseum:placetype": "airport",
    "wd:wordcount": 3418,
    "woe:hierarchy": {
      "country_id": 23424832,
      "planet_id": 1,
      "state_id": 24549725
    },
    "wof:name": "Anderson Air Force Base",
    "wof:placetype": "campus"
  },
  "geometry": {"coordinates":[144.929993,13.584],"type":"Point"}
}
