{
  "type": "Feature",
  "properties": {
    "name:ceb_x_preferred": [
      "Châteauroux-Centre \"\"Marcel Dassault\"\" Airport"
    ],
    "name:deu_x_preferred": [
      "Flughafen Châteauroux"
    ],
    "name:eng_x_preferred": [
      "Châteauroux-Centre \"Marcel Dassault\" Airport"
    ],
    "name:eng_x_variant": [
      "CHR",
      "LFLX"
    ],
    "name:fas_x_preferred": [
      "فرودگاه شاترو-سانتر"
    ],
    "name:fas_x_variant": [
      "فرودگاه شتورو-سنتر \"مارسل داساولت\""
    ],
    "name:fra_x_preferred": [
      "Aéroport de Châteauroux-Centre"
    ],
    "name:hun_x_preferred": [
      "Châteauroux repülőtér"
    ],
    "name:msa_x_preferred": [
      "Lapangan Terbang Deols"
    ],
    "name:ron_x_preferred": [
      "Aeroportul Châteauroux-Centre \"Marcel Dassault\""
    ],
    "name:tgk_x_preferred": [
      "Фурудгоҳи штуру-снтр морсил досовлт"
    ],
    "name:vie_x_preferred": [
      "Sân bay Châteauroux-Déols \"Marcel Dassault\""
    ],
    "name:zho_x_preferred": [
      "沙托魯-中央\"Marcel Dassault\"機場"
    ],
    "oa:elevation_ft": "529",
    "oa:type": "medium_airport",
    "sfomuseum:is_sfo": 1,
    "sfomuseum:placetype": "airport",
    "sfomuseum:repo": "sfomuseum-data-whosonfirst",
    "woe:hierarchy": {
      "country_id": 23424819,
      "county_id": 12597125,
      "localadmin_id": 12640653,
      "planet_id": 1,
      "state_id": 7153314
    },
    "wof:name": "Aéroport Marcel Dassault-Châteauroux Déols",
    "wof:placetype": "campus"
  },
  "geometry": {"coordinates":[1.73067,46.862202],"type":"Point"}
}
