{
  "type": "Feature",
  "properties": {
    "gn:country": "TW",
    "gn:fcode": "ADMD",
    "gn:population": 0,
    "iso:country": "TW",
    "name:ceb_x_preferred": [
      "Neihu Qu"
    ],
    "name:deu_x_preferred": [
      "Neihu"
    ],
    "name:eng_x_preferred": [
      "Neihu District"
    ],
    "name:hak_x_preferred": [
      "Nui-fù-khî"
    ],
    "name:hye_x_preferred": [
      "Նեյհու"
    ],
    "name:ind_x_preferred": [
      "Distrik Neihu"
    ],
    "name:jpn_x_preferred": [
      "内湖区"
    ],
    "name:kor_x_preferred": [
      "네이후구"
    ],
    "name:lit_x_preferred": [
      "Neihu"
    ],
    "name:lzh_x_preferred": [
      "內湖區"
    ],
    "name:nan_x_preferred": [
      "Lāi-ô͘-khu"
    ],
    "name:nld_x_preferred": [
      "Neihu District"
    ],
    "name:pol_x_preferred": [
      "Neihu"
    ],
    "name:rus_x_preferred": [
      "Нэйху"
    ],
    "name:ukr_x_preferred": [
      "Нейху"
    ],
    "name:vie_x_preferred": [
      "Nội Hồ"
    ],
    "name:yue_x_preferred": [
      "內湖區"
    ],
    "name:zho_x_preferred": [
      "Nei-hu Ch’ü"
    ],
    "name:zho_x_variant": [
      "內湖區"
    ],
    "qs:name": "Neihu Qu",
    "qs:photos_9r": 0,
    "qs:photos_sr": 0,
    "qs:pop_sr": "0",
    "sfomuseum:placetype": "localadmin",
    "sfomuseum:repo": "sfomuseum-data-whosonfirst",
    "wd:wordcount": 534,
    "wof:name": "Neihu Qu",
    "wof:placetype": "localadmin",
    "wof:population": 0
  },
  "geometry": {"coordinates":[121.58333,25.08333],"type":"Point"}
}
