{
  "type": "Feature",
  "properties": {
    "name:bar_x_preferred": [
      "Flughafen Del Bajío"
    ],
    "name:deu_x_preferred": [
      "Flughafen Del Bajío"
    ],
    "name:eng_x_preferred": [
      "Del Bajío International Airport"
    ],
    "name:eng_x_variant": [
      "BJX",
      "MMLO"
    ],
    "name:fas_x_preferred": [
      "فرودگاه بین‌المللی دل بایو"
    ],
    "name:fra_x_preferred": [
      "aéroport international del Bajío"
    ],
    "name:ind_x_preferred": [
      "Bandar Udara Internasional Del Bajío"
    ],
    "name:jpn_x_preferred": [
      "グアナフアト国際空港"
    ],
    "name:msa_x_preferred": [
      "Lapangan Terbang Antarabangsa De Guanajuato"
    ],
    "name:pol_x_preferred": [
      "Port lotniczy León-Del Bajío"
    ],
    "name:ron_x_preferred": [
      "Aeroportul Internațional Del Bajío"
    ],
    "name:rus_x_preferred": [
      "Гуанахуато"
    ],
    "name:spa_x_preferred": [
      "Aeropuerto Internacional Del Bajío"
    ],
    "name:swe_x_preferred": [
      "Del Bajío International Airport"
    ],
    "name:tgk_x_preferred": [
      "Фурудгоҳи бин‌алмилалӣ дил бою"
    ],
    "name:vie_x_preferred": [
      "Sân bay quốc tế Del Bajío"
    ],
    "name:zho_x_preferred": [
      "Del Bajío國際機場"
    ],
    "oa:elevation_ft": "5956",
    "oa:type": "medium_airport",
    "sfomuseum:is_sfo": 1,
    "sfomuseum:placetype": "airport",
    "sfomuseum:repo": "sfomuseum-data-whosonfirst",
    "woe:hierarchy": {
      "country_id": 23424900,
      "county_id": 12600025,
      "planet_id": 1,
      "state_id": 2346274
    },
    "wof:name": "Silao Airport",
    "wof:placetype": "campus"
  },
  "geometry": {"coordinates":[-101.481003,20.9935],"type":"Point"}
}
