{
  "type": "Feature",
  "properties": {
    "name:ara_x_preferred": [
      "مطار قندهار الدولي"
    ],
    "name:deu_x_preferred": [
      "Flughafen Kandahar"
    ],
    "name:fas_x_preferred": [
      "میدان هوایی بین‌المللی قندهار"
    ],
    "name:fin_x_preferred": [
      "Kandaharin kansainvälinen lentoasema"
    ],
    "name:hin_x_preferred": [
      "कांधार अन्तर्राष्ट्रीय विमानक्षेत्र"
    ],
    "name:ind_x_preferred": [
      "Bandar Udara Kandahar"
    ],
    "name:jpn_x_preferred": [
      "カンダハール国際空港"
    ],
    "name:kor_x_preferred": [
      "칸다하르 국제공항"
    ],
    "name:mar_x_preferred": [
      "कंदहार आंतरराष्ट्रीय विमानतळ"
    ],
    "name:msa_x_preferred": [
      "Lapangan Terbang Kandahar"
    ],
    "name:nob_x_preferred": [
      "Kandahar internasjonale lufthavn"
    ],
    "name:pol_x_preferred": [
      "Port lotniczy Kandahar"
    ],
    "name:pus_x_preferred": [
      "د کندهار نړيوال هوايي ډګر"
    ],
    "name:ron_x_preferred": [
      "Aeroportul Internațional Kandahar"
    ],
    "name:rus_x_preferred": [
      "Кандагар"
    ],
    "name:tur_x_preferred": [
      "Kandehar Uluslararası Havalimanı"
    ],
    "name:zho_x_preferred": [
      "坎大哈国际机场"
    ],
    "oa:elevation_ft": "3337",
    "oa:type": "medium_airport",
    "sfomuseum:is_sfo": 1,
    "sfomuseum:placetype": "airport",
    "sfomuseum:repo": "sfomuseum-data-whosonfirst",
    "wd:wordcount": 2177,
    "woe:hierarchy": {
      "country_id": 23424739,
      "county_id": 56000686,
      "planet_id": 1,
      "state_id": 2344569
    },
    "wof:name": "Kandahar International Airport",
    "wof:placetype": "campus"
  },
  "geometry": {"coordinates":[65.850278,31.507222],"type":"Point"}
}
